README.rst
_description.org
lh-agpl3-LICENSE.txt
pyproject.toml
setup.py
bin/cntnrCharActivate.cs
bin/cntnrCharName.cs
bin/cntnrCharThis.cs
bisos/__init__.py
bisos.cntnr.egg-info/PKG-INFO
bisos.cntnr.egg-info/SOURCES.txt
bisos.cntnr.egg-info/dependency_links.txt
bisos.cntnr.egg-info/not-zip-safe
bisos.cntnr.egg-info/requires.txt
bisos.cntnr.egg-info/top_level.txt
bisos/cntnr/__init__.py
bisos/cntnr/cntnrCharName.py
bisos/cntnr/cntnrCharThis.py
bisos/cntnr/curFps.py